drf_crypto/__init__.py
drf_crypto/admin.py
drf_crypto/apps.py
drf_crypto/migrations/0001_initial.py
drf_crypto/migrations/__init__.py
drf_crypto/models.py
drf_crypto/py.typed
drf_crypto/serializers.py
drf_crypto/settings.py
drf_crypto/urls.py
drf_crypto/views.py
drf_crypto-0.1.2.dist-info/WHEEL
drf_crypto-0.1.2.dist-info/METADATA
drf_crypto-0.1.2.dist-info/license_files/LICENSE
drf_crypto-0.1.2.dist-info/RECORD
