Metadata-Version: 2.1
Name: drf-crypto
Version: 0.1.2
Summary: Provide crypto payment essential to the drf-shop
Author-email: Xurvan <xurvan@tutanota.com>
Requires-Python: >=3.10
Requires-Dist: drf-shop>=0.1.1
Provides-Extra: dev
Requires-Dist: pre-commit>=2.20.0; extra == "dev"
Project-URL: source, https://github.com/xanigo/drf-crypto
